Workbook

Sheet 00_README
A1: GULGO — Jeux de tests et recette Score Pass V1
A2: Validation de conformité du moteur par rapport au Manuel méthodologique, aux Spécifications fonctionnelles et au Paramétrage V1 pré-pilote.
A4: Élément | B4: Contenu
A5: Objectif | B5: Vérifier le comportement fonctionnel du moteur Score Pass avant recette et mise en pilote.
A6: Documents de référence | B6: Manuel méthodologique Score Pass V1 ; Spécifications fonctionnelles du moteur Score Pass V1 ; Paramétrage du moteur Score Pass V1.xlsx.
A7: Nature des tests | B7: Calcul, applicabilité, données manquantes, preuves, IQP, hard gates, versionnage, restitution, audit trail et sécurité.
A8: Paramètres non calibrés | B8: Les tests ne figent pas les seuils, classes, niveaux minimaux de preuve ou règles sectorielles encore marqués « À calibrer ».
A9: Principe de recette | B9: Conforme uniquement si le résultat observé correspond au résultat attendu et si la traçabilité requise est complète.
A10: Important | B10: Les cas numériques fondés sur les poids D1–D6 V1 servent à la recette technique ; ils ne valident pas définitivement les pondérations.
A11: Version du classeur | B11: V1.0 — pré-pilote
A12: Date | B12: 2026-08-31

Sheet 01_Catalogue_Tests
A1: 01 — Catalogue des tests de recette
A2: Chaque scénario possède un résultat attendu vérifiable indépendamment de l’interface technique retenue.
A4: Test_ID | B4: Famille | C4: Scénario | D4: Précondition | E4: Entrée clé | F4: Résultat attendu | G4: Criticité | H4: Automatisable | I4: Statut recette | J4: Responsable | K4: Commentaire
A5: T01 | B5: Calcul | C5: Dossier complet sans anomalie | D5: Version V1.0 active | E5: D1–D6 évaluables | F5: Score Pass, IQP et couverture produits | G5: Critique | H5: Oui | I5: À exécuter
A6: T02 | B6: Applicabilité | C6: Élément réellement non applicable | D6: Règle NA active | E6: NOT_APPLICABLE | F6: Exclusion du calcul et renormalisation si prévue | G6: Critique | H6: Oui | I6: À exécuter
A7: T03 | B7: Données manquantes | C7: Donnée applicable manquante | D7: Variable applicable | E7: NOT_EVALUABLE_MISSING | F7: Aucune conversion en 0 ; contrôle couverture | G7: Critique | H7: Oui | I7: À exécuter
A8: T04 | B8: Valeur zéro | C8: Valeur économique réellement égale à zéro | D8: Variable évaluable | E8: Valeur = 0 | F8: 0 traité comme valeur réelle | G8: Critique | H8: Oui | I8: À exécuter
A9: T05 | B9: Cold start | C9: Historique insuffisant | D9: Entreprise récente | E9: COLD_START | F9: Profil en constitution si nécessaire ; aucune pénalité automatique liée à l’âge | G9: Importante | H9: Oui | I9: À exécuter
A10: T06 | B10: Preuve | C10: Variable critique avec preuve insuffisante | D10: Minimum de preuve configuré | E10: Preuve < minimum | F10: Contrôle suspensif/bloquant selon paramètre | G10: Critique | H10: Oui | I10: À exécuter
A11: T07 | B11: Hard gate | C11: HG1 activé | D11: Identité/existence non établie | E11: HG1 actif | F11: Score global non produit tant que gate non levé | G11: Critique | H11: Oui | I11: À exécuter
A12: T08 | B12: Anomalie | C12: Anomalie A2 résolue | D12: Anomalie enregistrée | E12: A2 puis clôturée | F12: Historique conservé ; calcul autorisé après traitement | G12: Importante | H12: Partiel | I12: À exécuter
A13: T09 | B13: Exception | C13: Exception méthodologique approuvée | D13: Autorisation conforme RACI | E13: Exception validée | F13: Traitement appliqué et visible dans audit trail | G13: Critique | H13: Partiel | I13: À exécuter
A14: T10 | B14: Reproductibilité | C14: Même dossier, mêmes paramètres | D14: Données/version identiques | E14: Deux calculs | F14: Résultat strictement identique | G14: Critique | H14: Oui | I14: À exécuter
A15: T11 | B15: Versionnage | C15: Nouvelle version du modèle | D15: Score historique V1.0 existe | E15: Recalcul V1.1/V2.0 | F15: Score historique inchangé ; recalcul distinct | G15: Critique | H15: Oui | I15: À exécuter
A16: T12 | B16: Correction | C16: Correction après restitution | D16: Erreur factuelle confirmée | E16: Valeur corrigée | F16: Score initial conservé ; score corrigé tracé | G16: Critique | H16: Partiel | I16: À exécuter
... A24: T20 | B24: Sécurité | C24: Rôle sans droit méthodologique | D24: Utilisateur restreint | E24: Tentative modification poids | F24: Modification refusée et journalisée | G24: Critique | H24: Partiel | I24: À exécuter

Sheet 02_Cas_Numeriques
A1: 02 — Cas numériques de référence
A2: Poids V1 : D1 15 %, D2 20 %, D3 20 %, D4 20 %, D5 15 %, D6 10 %. Les cas testent l’agrégation et la renormalisation.
A4: Case_ID | B4: Description | C4: D1 | D4: D2 | E4: D3 | F4: D4 | G4: D5 | H4: D6 | I4: Score interne calculé | J4: Score externe | K4: IQP | L4: Couverture | M4: Hard gate | N4: Statut attendu | O4: Cible interne | P4: Tolérance | Q4: Contrôle | R4: But
A5: N01 | B5: Cas complet de référence | C5: 90 | D5: 70 | E5: 80 | F5: 75 | G5: 65 | H5: 60 | I5: =(IF(ISNUMBER(C5),C5*0.15,0)+IF(ISNUMBER(D5),D5*0.2,0)+IF(ISNUMBER(E5),E5*0.2,0)+IF(ISNUMBER(F5),F5*0.2,0)+IF(ISNUMBER(G5),G5*0.15,0)+IF(ISNUMBER(H5),H5*0.1,0))/(IF(ISNUMBER(C5),0.15,0)+IF(ISNUMBER(D5),0.2,0)+IF(ISNUMBER(E5),0.2,0)+IF(ISNUMBER(F5),0.2,0)+IF(ISNUMBER(G5),0.15,0)+IF(ISNUMBER(H5),0.1,0)) -> 74.25 | J5: =IF(M5="Non",ROUND(I5,0),"") -> 74 | K5: 79.25 | L5: 1 | M5: Non | N5: SCORE_PRODUCED | O5: 74.25 | P5: 0.0001 | Q5: =IF(ABS(I5-O5)<=P5,"OK","ECART") -> OK | R5: Agrégation standard + arrondi
A6: N02 | B6: Score élevé / IQP faible | C6: 92 | D6: 85 | E6: 88 | F6: 82 | G6: 78 | H6: 75 | I6: =(IF(ISNUMBER(C6),C6*0.15,0)+IF(ISNUMBER(D6),D6*0.2,0)+IF(ISNUMBER(E6),E6*0.2,0)+IF(ISNUMBER(F6),F6*0.2,0)+IF(ISNUMBER(G6),G6*0.15,0)+IF(ISNUMBER(H6),H6*0.1,0))/(IF(ISNUMBER(C6),0.15,0)+IF(ISNUMBER(D6),0.2,0)+IF(ISNUMBER(E6),0.2,0)+IF(ISNUMBER(F6),0.2,0)+IF(ISNUMBER(G6),0.15,0)+IF(ISNUMBER(H6),0.1,0)) -> 84 | J6: =IF(M6="Non",ROUND(I6,0),"") -> 84 | K6: 42 | L6: 1 | M6: Non | N6: SCORE_PRODUCED | O6: 84 | P6: 0.0001 | Q6: =IF(ABS(I6-O6)<=P6,"OK","ECART") -> OK | R6: Indépendance Score / IQP
A7: N03 | B7: Score faible / IQP élevé | C7: 45 | D7: 50 | E7: 48 | F7: 55 | G7: 40 | H7: 50 | I7: =(IF(ISNUMBER(C7),C7*0.15,0)+IF(ISNUMBER(D7),D7*0.2,0)+IF(ISNUMBER(E7),E7*0.2,0)+IF(ISNUMBER(F7),F7*0.2,0)+IF(ISNUMBER(G7),G7*0.15,0)+IF(ISNUMBER(H7),H7*0.1,0))/(IF(ISNUMBER(C7),0.15,0)+IF(ISNUMBER(D7),0.2,0)+IF(ISNUMBER(E7),0.2,0)+IF(ISNUMBER(F7),0.2,0)+IF(ISNUMBER(G7),0.15,0)+IF(ISNUMBER(H7),0.1,0)) -> 48.35 | J7: =IF(M7="Non",ROUND(I7,0),"") -> 48 | K7: 92 | L7: 1 | M7: Non | N7: SCORE_PRODUCED | O7: 48.35 | P7: 0.0001 | Q7: =IF(ABS(I7-O7)<=P7,"OK","ECART") -> OK | R7: Indépendance Score / IQP
A8: N04 | B8: D6 non applicable | C8: 80 | D8: 70 | E8: 75 | F8: 65 | G8: 60 | I8: =(IF(ISNUMBER(C8),C8*0.15,0)+IF(ISNUMBER(D8),D8*0.2,0)+IF(ISNUMBER(E8),E8*0.2,0)+IF(ISNUMBER(F8),F8*0.2,0)+IF(ISNUMBER(G8),G8*0.15,0)+IF(ISNUMBER(H8),H8*0.1,0))/(IF(ISNUMBER(C8),0.15,0)+IF(ISNUMBER(D8),0.2,0)+IF(ISNUMBER(E8),0.2,0)+IF(ISNUMBER(F8),0.2,0)+IF(ISNUMBER(G8),0.15,0)+IF(ISNUMBER(H8),0.1,0)) -> 70 | J8: =IF(M8="Non",ROUND(I8,0),"") -> 70 | K8: 76 | L8: 1 | M8: Non | N8: SCORE_PRODUCED | O8: 70 | P8: 0.0001 | Q8: =IF(ABS(I8-O8)<=P8,"OK","ECART") -> OK | R8: Renormalisation sans D6
A9: N05 | B9: Score brut élevé mais HG1 actif | C9: 95 | D9: 90 | E9: 85 | F9: 90 | G9: 80 | H9: 85 | I9: =(IF(ISNUMBER(C9),C9*0.15,0)+IF(ISNUMBER(D9),D9*0.2,0)+IF(ISNUMBER(E9),E9*0.2,0)+IF(ISNUMBER(F9),F9*0.2,0)+IF(ISNUMBER(G9),G9*0.15,0)+IF(ISNUMBER(H9),H9*0.1,0))/(IF(ISNUMBER(C9),0.15,0)+IF(ISNUMBER(D9),0.2,0)+IF(ISNUMBER(E9),0.2,0)+IF(ISNUMBER(F9),0.2,0)+IF(ISNUMBER(G9),0.15,0)+IF(ISNUMBER(H9),0.1,0)) -> 87.75 | J9: =IF(M9="Non",ROUND(I9,0),"") | K9: 88 | L9: 1 | M9: HG1 | N9: INCOMPLETE | O9: 87.75 | P9: 0.0001 | Q9: =IF(ABS(I9-O9)<=P9,"OK","ECART") -> OK | R9: Gate hors compensation

Sheet 03_Tests_IQP
A1: 03 — Tests du calcul IQP
A2: Formule V1 : IQP = 0,40 E + 0,20 C + 0,15 F + 0,15 Co + 0,10 T.
A4: Case_ID | B4: Description | C4: E | D4: C | E4: F | F4: Co | G4: T | H4: IQP calculé | I4: IQP cible | J4: Écart | K4: Contrôle | L4: But
A5: IQP01 | B5: Cas de référence | C5: 80 | D5: 70 | E5: 90 | F5: 75 | G5: 85 | H5: =C5*0.4+D5*0.2+E5*0.15+F5*0.15+G5*0.1 -> 79.25 | I5: 79.25 | J5: =H5-I5 -> 0 | K5: =IF(ABS(J5)<0.0001,"OK","ECART") -> OK | L5: Vérifier formule
A6: IQP02 | B6: Toutes composantes à 100 | C6: 100 | D6: 100 | E6: 100 | F6: 100 | G6: 100 | H6: =C6*0.4+D6*0.2+E6*0.15+F6*0.15+G6*0.1 -> 100 | I6: 100 | J6: =H6-I6 -> 0 | K6: =IF(ABS(J6)<0.0001,"OK","ECART") -> OK | L6: Maximum
A7: IQP03 | B7: Toutes composantes à 0 | C7: 0 | D7: 0 | E7: 0 | F7: 0 | G7: 0 | H7: =C7*0.4+D7*0.2+E7*0.15+F7*0.15+G7*0.1 -> 0 | I7: 0 | J7: =H7-I7 -> 0 | K7: =IF(ABS(J7)<0.0001,"OK","ECART") -> OK | L7: Minimum
A8: IQP04 | B8: Étayage faible, autres élevés | C8: 25 | D8: 90 | E8: 90 | F8: 90 | G8: 90 | H8: =C8*0.4+D8*0.2+E8*0.15+F8*0.15+G8*0.1 -> 64 | I8: 64 | J8: =H8-I8 -> 0 | K8: =IF(ABS(J8)<0.0001,"OK","ECART") -> OK | L8: Poids dominant de l’étayage

Sheet 04_Statuts_Donnees
A1: 04 — Matrice de tests des statuts de données
A2: Contrôle de la distinction entre valeur zéro, manquant, NA, non-évaluable, cold start, refus et vérification.
A4: Test_ID | B4: Entrée | C4: Code statut | D4: Scoré ? | E4: Valeur 0 ? | F4: Renormalisation auto ? | G4: Contrôle supplémentaire ? | H4: Résultat attendu | I4: Recette
A5: S01 | B5: Valeur réellement égale à 0 | C5: EVALUABLE | D5: Oui | E5: Oui | F5: Non | G5: Non | H5: 0 est une valeur valide | I5: À exécuter
A6: S02 | B6: Information absente | C6: NOT_EVALUABLE_MISSING | D6: Non | E6: Non | F6: Non | G6: Oui | H6: Contrôle couverture/criticité | I6: À exécuter
A7: S03 | B7: Élément réellement non applicable | C7: NOT_APPLICABLE | D7: Non | E7: Non | F7: Oui si règle active | G7: Non | H7: Exclusion du calcul | I7: À exécuter
A8: S04 | B8: Preuve insuffisante | C8: NOT_EVALUABLE_EVIDENCE | D8: Non | E8: Non | F8: Non | G8: Oui | H8: Contrôle preuve minimum | I8: À exécuter
A9: S05 | B9: Historique insuffisant | C9: COLD_START | D9: Selon indicateur | E9: Non | F9: Non | G9: Oui | H9: Profil en constitution si nécessaire | I9: À exécuter
A10: S06 | B10: Information temporairement indisponible | C10: TEMP_UNAVAILABLE | D10: Non temporairement | E10: Non | F10: Non | G10: Oui | H10: Dossier peut rester en cours | I10: À exécuter
A11: S07 | B11: Refus de transmission | C11: REFUSED | D11: Non | E11: Non | F11: Non | G11: Oui | H11: Tracer refus ; hard gate possible si critique | I11: À exécuter
A12: S08 | B12: Sous vérification | C12: UNDER_VERIFICATION | D12: Non jusqu’à clôture | E12: Non | F12: Non | G12: Oui | H12: Ne pas figer résultat prématurément | I12: À exécuter

Sheet 05_Tests_Hard_Gates
A1: 05 — Tests des hard gates
A2: Les hard gates sont évalués indépendamment du score numérique.
A4: Test_ID | B4: Gate | C4: Situation | D4: Score brut possible | E4: Effet attendu | F4: Score officiel ? | G4: Statut attendu | H4: Condition de levée | I4: Résultat observé | J4: Recette
A5: HG-T01 | B5: HG1 | C5: Identité/existence impossible à établir | D5: 88.25 | E5: Suspendre ou bloquer | F5: Non | G5: INCOMPLETE | H5: Établir identité/existence selon procédure | J5: À exécuter
A6: HG-T02 | B6: HG2 | C6: Activité incompatible avec le périmètre | D6: 72 | E6: Interrompre l’évaluation normale | F6: Non | G6: INTERRUPTED | H6: Décision de périmètre ou gouvernance | J6: À exécuter
A7: HG-T03 | B7: HG3 | C7: Falsification substantielle établie | D7: 81 | E7: Bloquer / escalader | F7: Non | G7: SUSPENDED | H7: Décision formelle et traitement selon cas | J7: À exécuter
A8: HG-T04 | B8: HG4 | C8: Refus d’une information critique indispensable | D8: 76 | E8: Suspendre ou bloquer | F8: Non | G8: SUSPENDED | H8: Transmission ou décision formelle | J8: À exécuter
A9: HG-T05 | B9: Aucun | C9: Aucun hard gate actif | D9: 74.25 | E9: Poursuivre | F9: Oui | G9: SCORE_PRODUCED | H9: N/A | J9: À exécuter

Sheet 06_Tests_Versionnage
A1: 06 — Tests de versionnage et reproductibilité
A2: Une nouvelle version ne doit jamais écraser un Score Pass officiel historique.
A4: Test_ID | B4: Étape | C4: Evaluation_ID | D4: Version modèle | E4: Données | F4: Score attendu | G4: Nature résultat | H4: Remplace précédent ? | I4: Audit trail requis | J4: Résultat observé | K4: Recette
A5: V01-1 | B5: Calcul initial | C5: SP-2026-0001 | D5: V1.0 | E5: Dataset A | F5: 74 | G5: Officiel | H5: N/A | I5: Oui | K5: À exécuter
A6: V01-2 | B6: Recalcul identique | C6: SP-2026-0001-R | D6: V1.0 | E6: Dataset A | F6: 74 | G6: Contrôle reproductibilité | H6: Non | I6: Oui | K6: À exécuter
A7: V02-1 | B7: Recalcul nouvelle version | C7: SP-2026-0001-A | D7: V1.1 | E7: Dataset A | F7: Selon V1.1 | G7: Analytique | H7: Non | I7: Oui | K7: À exécuter
A8: V03-1 | B8: Correction factuelle | C8: SP-2026-0001-C | D8: V1.0 | E8: Dataset A corrigé | F8: Recalculé | G8: Correction officielle | H8: Non : original conservé | I8: Oui | K8: À exécuter

Sheet 07_Tests_Restitution
A1: 07 — Tests de restitution
A2: Contrôle des champs et mentions obligatoires dans toute sortie officielle.
A4: Test_ID | B4: Élément | C4: Obligatoire | D4: Condition | E4: Format attendu | F4: Présent ? | G4: Conforme ? | H4: Commentaire | I4: Recette
A5: R01 | B5: Identifiant entreprise | C5: Oui | D5: Toujours | E5: enterprise_id | I5: À exécuter
A6: R02 | B6: Identifiant évaluation | C6: Oui | D6: Toujours | E6: evaluation_id unique | I6: À exécuter
A7: R03 | B7: Version méthodologique | C7: Oui | D7: Toujours | E7: Vx.y | I7: À exécuter
A8: R04 | B8: Date d’évaluation | C8: Oui | D8: Toujours | E8: Date | I8: À exécuter
A9: R05 | B9: Période observée | C9: Oui | D9: Toujours | E9: Période/date range | I9: À exécuter
A10: R06 | B10: Score Pass | C10: Conditionnel | D10: Si score produit | E10: X/100, jamais X % | I10: À exécuter
A11: R07 | B11: Scores D1–D6 | C11: Oui si évaluables | D11: Selon applicabilité | E11: 0–100 | I11: À exécuter
A12: R08 | B12: IQP | C12: Oui | D12: Si évaluation | E12: /100 | I12: À exécuter
A13: R09 | B13: Couverture | C13: Oui | D13: Si évaluation | E13: % ou ratio identifié | I13: À exécuter
A14: R10 | B14: Statut fraîcheur | C14: Oui | D14: Toujours | E14: À jour / À actualiser / Expiré | I14: À exécuter
A15: R11 | B15: Réserves / limites | C15: Oui | D15: Toujours | E15: Texte/listes | I15: À exécuter
A16: R12 | B16: Mention méthodologique obligatoire | C16: Oui | D16: Restitution externe | E16: Texte intégral validé | I16: À exécuter
A19: Mention méthodologique obligatoire
A20: Le Score Pass constitue une information structurée de crédibilité économique fondée sur les données et preuves disponibles à la date de l’évaluation. Il ne constitue ni une notation de crédit, ni une probabilité de défaut, ni une garantie de solvabilité, de remboursement, de performance future ou d’accès au financement. Toute décision économique, commerciale, financière ou d’investissement relève exclusivement du décideur concerné.

Sheet 08_Execution_Recette
A1: 08 — Feuille d’exécution de la recette
A2: À compléter pendant la recette avec l’ingénieur. Chaque écart doit être rattaché à une anomalie ou un correctif.
A4: Test_ID | B4: Date | C4: Version moteur | D4: Version modèle | E4: Testeur | F4: Résultat attendu | G4: Résultat observé | H4: Statut | I4: Bug_ID | J4: Preuve / capture | K4: Commentaire | L4: Visa
A5: T01 | D5: V1.0 | H5: À exécuter
A6: T02 | D6: V1.0 | H6: À exécuter
A7: T03 | D7: V1.0 | H7: À exécuter
A8: T04 | D8: V1.0 | H8: À exécuter
A9: T05 | D9: V1.0 | H9: À exécuter
A10: T06 | D10: V1.0 | H10: À exécuter
A11: T07 | D11: V1.0 | H11: À exécuter
A12: T08 | D12: V1.0 | H12: À exécuter
A13: T09 | D13: V1.0 | H13: À exécuter
A14: T10 | D14: V1.0 | H14: À exécuter
A15: T11 | D15: V1.0 | H15: À exécuter
A16: T12 | D16: V1.0 | H16: À exécuter
... A24: T20 | D24: V1.0 | H24: À exécuter

Sheet 09_Registre_Anomalies
A1: 09 — Registre des anomalies de recette
A2: Suivi des écarts entre résultat attendu et comportement du moteur.
A4: Bug_ID | B4: Test_ID | C4: Date ouverture | D4: Description | E4: Criticité | F4: Module | G4: Version moteur | H4: Statut | I4: Responsable | J4: Correctif prévu | K4: Date correction | L4: Retest | M4: Décision recette
A5: BUG-001 | H5: Ouvert
A6: BUG-002 | H6: Ouvert
A7: BUG-003 | H7: Ouvert
A8: BUG-004 | H8: Ouvert
A9: BUG-005 | H9: Ouvert
A10: BUG-006 | H10: Ouvert
A11: BUG-007 | H11: Ouvert
A12: BUG-008 | H12: Ouvert
A13: BUG-009 | H13: Ouvert
A14: BUG-010 | H14: Ouvert
A15: BUG-011 | H15: Ouvert
A16: BUG-012 | H16: Ouvert
... A24: BUG-020 | H24: Ouvert

Sheet 10_Synthese_Recette
A1: 10 — Synthèse de recette
A2: Tableau de bord pour la décision GO / ITERATE / PIVOT / NO-GO.
A4: Indicateur | B4: Valeur | D4: Critère | E4: GO | F4: ITERATE | G4: PIVOT | H4: NO-GO
A5: Tests catalogués | B5: 20 | D5: Tests critiques | E5: Tous conformes | F5: Écarts corrigeables | G5: Écarts structurants | H5: Échec règles fondamentales
A6: Tests conformes | B6: =COUNTIF('08_Execution_Recette'!H5:H24,"Conforme") -> 0 | D6: Reproductibilité | E6: Démontrée | F6: Correction mineure | G6: Architecture à revoir | H6: Non démontrée
A7: Tests non conformes | B7: =COUNTIF('08_Execution_Recette'!H5:H24,"Non conforme") -> 0 | D7: Hard gates | E7: Conformes | F7: Ajustement local | G7: Logique à revoir | H7: Contournables/inopérants
A8: Tests bloqués | B8: =COUNTIF('08_Execution_Recette'!H5:H24,"Bloqué") -> 0 | D8: Versionnage | E8: Conforme | F8: Correction mineure | G8: Architecture à revoir | H8: Écrase l’historique
A9: Tests non exécutés | B9: =COUNTIF('08_Execution_Recette'!H5:H24,"À exécuter") -> 20 | D9: Audit trail | E9: Complet | F9: Lacunes mineures | G9: Lacunes majeures | H9: Non exploitable
A10: Taux de conformité | B10: =IFERROR(B6/(B5-B9),0) -> 0 | D10: Décision finale
A11: Anomalies critiques ouvertes | B11: =COUNTIFS('09_Registre_Anomalies'!E5:E24,"Critique",'09_Registre_Anomalies'!H5:H24,"<>Clos") -> 0

Sheet 11_Checklist_PreProd
A1: 11 — Checklist avant pré-production
A2: La mise en pilote ne doit intervenir qu’après validation des éléments bloquants.
A4: ID | B4: Contrôle | C4: Obligatoire | D4: État | E4: Responsable | F4: Preuve | G4: Bloquant ? | H4: Commentaire
A5: PP01 | B5: Dictionnaire des variables finalisé | C5: Oui | G5: Oui
A6: PP02 | B6: Formules des 24 indicateurs formalisées | C6: Oui | G6: Oui
A7: PP03 | B7: Règles de normalisation paramétrées | C7: Oui | G7: Oui
A8: PP04 | B8: Poids internes validés pour le pilote | C8: Oui | G8: Oui
A9: PP05 | B9: Règles de couverture définies | C9: Oui | G9: Oui
A10: PP06 | B10: Niveaux minimaux de preuve définis pour variables critiques | C10: Oui | G10: Oui
A11: PP07 | B11: Hard gates configurés et testés | C11: Oui | G11: Oui
A12: PP08 | B12: IQP calculé séparément du Score Pass | C12: Oui | G12: Oui
A13: PP09 | B13: Versionnage et non-rétroactivité testés | C13: Oui | G13: Oui
A14: PP10 | B14: Audit trail fonctionnel | C14: Oui | G14: Oui
A15: PP11 | B15: Restitution avec mention méthodologique | C15: Oui | G15: Oui
A16: PP12 | B16: Jeux de tests critiques conformes | C16: Oui | G16: Oui
... A19: PP15 | B19: Décision GO / ITERATE / PIVOT / NO-GO formalisée | C19: Oui | G19: Oui
