Workbook

Sheet 00_README
A1: GULGO — Paramétrage du moteur Score Pass V1
A2: Livrable technique compagnon des Spécifications fonctionnelles et du Manuel méthodologique. Statut : V1 pré-pilote.
A4: Élément | B4: Contenu
A5: Finalité | B5: Fournir à l’ingénieur les objets, paramètres, statuts et règles configurables nécessaires au moteur Score Pass.
A6: Référentiel méthodologique | B6: Manuel méthodologique Score Pass V1 — chapitres 1 à 14.
A7: Référentiel fonctionnel | B7: Spécifications fonctionnelles du moteur Score Pass V1.
A8: Principe d’implémentation | B8: Les règles susceptibles d’évoluer doivent être paramétrables et versionnées ; elles ne doivent pas être codées en dur.
A9: Valeurs provisoires | B9: Toute cellule ou ligne portant le statut « À calibrer » ou « À formaliser » ne constitue pas une règle définitive.
A10: Règle d’arbitrage | B10: L’ingénieur ne complète pas une lacune méthodologique par une hypothèse implicite. Toute ambiguïté est remontée au Responsable Méthode.
A11: Sorties distinctes | B11: Score Pass /100, IQP /100 et couverture méthodologique sont trois résultats distincts.
A12: Version du fichier | B12: V1.0 — pré-pilote
A13: Date de préparation | B13: 46265

Sheet 01_Dimensions
A1: 01 — Dimensions Score Pass V1
A2: Les pondérations sont des paramètres V1 pré-pilote et doivent rester configurables.
A4: Code | B4: Dimension | C4: Objet général | D4: Poids V1 | E4: Statut | F4: Version
A5: D1 | B5: Identité & existence | C5: Établir l’identité, l’existence et la réalité observable de l’entreprise | D5: 0.15 | E5: À calibrer | F5: V1.0
A6: D2 | B6: Traçabilité & qualité des données | C6: Apprécier la disponibilité, la cohérence et la traçabilité des informations | D6: 0.2 | E6: À calibrer | F6: V1.0
A7: D3 | B7: Activité & régularité économique | C7: Évaluer la réalité, la continuité et la régularité de l’activité | D7: 0.2 | E7: À calibrer | F7: V1.0
A8: D4 | B8: Discipline & engagements | C8: Apprécier la manière dont l’entreprise respecte et documente ses engagements | D8: 0.2 | E8: À calibrer | F8: V1.0
A9: D5 | B9: Performance & résilience | C9: Apprécier la performance économique observée et certaines fragilités susceptibles d’affecter sa continuité | D9: 0.15 | E9: À calibrer | F9: V1.0
A10: D6 | B10: Formalisation & gouvernance | C10: Évaluer le niveau d’organisation, de formalisation et de gouvernance adapté au profil de l’entreprise | D10: 0.1 | E10: À calibrer | F10: V1.0
A11: TOTAL | D11: =SUM(D5:D10) -> 1

Sheet 02_Indicateurs
A1: 02 — Dictionnaire des indicateurs V1
A2: 24 indicateurs initiaux, quatre par dimension. Les méthodes de calcul et seuils détaillés restent à formaliser/calibrer.
A4: Code | B4: Dimension | C4: Indicateur | D4: Variables principales | E4: Type | F4: Applicabilité | G4: Normalisation | H4: Poids interne | I4: Preuve min. | J4: Criticité | K4: Statut V1 | L4: Version | M4: Commentaire technique
A5: D1.1.1 | B5: D1 | C5: Identité de l’entreprise établie | D5: Dénomination ou nom commercial; forme juridique; numéro(s) officiel(s) d’identification; statut d’enregistrement | E5: Qualitatif | F5: Applicable | G5: À formaliser | I5: À calibrer | J5: Critique | K5: À calibrer | L5: V1.0 | M5: L’absence d’identifiant officiel ne doit pas produire automatiquement un zéro.
A6: D1.2.1 | B6: D1 | C6: Responsables identifiés | D6: Dirigeants; représentants | E6: Qualitatif | F6: Applicable | G6: À formaliser | I6: À calibrer | J6: Importante | K6: À calibrer | L6: V1.0
A7: D1.3.1 | B7: D1 | C7: Localisation observable | D7: Adresse; lieu d’activité | E7: Mixte | F7: Applicable | G7: À formaliser | I7: À calibrer | J7: Importante | K7: À calibrer | L7: V1.0
A8: D1.4.1 | B8: D1 | C8: Ancienneté de l’activité | D8: Date de début; durée | E8: Quantitatif | F8: Applicable | G8: À formaliser | I8: À calibrer | J8: Secondaire | K8: À calibrer | L8: V1.0 | M8: Cold start à distinguer d’une faiblesse.
A9: D2.1.1 | B9: D2 | C9: Disponibilité des données essentielles | D9: Variables disponibles | E9: Quantitatif | F9: Applicable | G9: À formaliser | I9: À calibrer | J9: Importante | K9: À calibrer | L9: V1.0
A10: D2.2.1 | B10: D2 | C10: Cohérence des informations | D10: Écarts et contradictions | E10: Mixte | F10: Applicable | G10: À formaliser | I10: À calibrer | J10: Importante | K10: À calibrer | L10: V1.0
A11: D2.3.1 | B11: D2 | C11: Traçabilité documentaire | D11: Sources et pièces associées | E11: Mixte | F11: Applicable | G11: À formaliser | I11: À calibrer | J11: Importante | K11: À calibrer | L11: V1.0
A12: D2.4.1 | B12: D2 | C12: Actualisation des informations | D12: Dates des données | E12: Quantitatif | F12: Applicable | G12: À formaliser | I12: À calibrer | J12: Secondaire | K12: À calibrer | L12: V1.0
A13: D3.1.1 | B13: D3 | C13: Continuité de l’activité | D13: Périodes d’activité | E13: Quantitatif | F13: Applicable | G13: À formaliser | I13: À calibrer | J13: Importante | K13: À calibrer | L13: V1.0
A14: D3.2.1 | B14: D3 | C14: Régularité de l’activité observée | D14: Mois actifs; interruptions | E14: Quantitatif | F14: Applicable | G14: À formaliser | I14: À calibrer | J14: Importante | K14: À calibrer | L14: V1.0
A15: D3.3.1 | B15: D3 | C15: Concentration de l’activité | D15: Clients ou sources principales | E15: Quantitatif | F15: Applicable | G15: À formaliser | I15: À calibrer | J15: Importante | K15: À calibrer | L15: V1.0
A16: D3.4.1 | B16: D3 | C16: Stabilité de l’activité | D16: Variations importantes | E16: Mixte | F16: Applicable | G16: À formaliser | I16: À calibrer | J16: Importante | K16: À calibrer | L16: V1.0
A17: D4.1.1 | B17: D4 | C17: Respect des engagements observables | D17: Incidents documentés | E17: Mixte | F17: Applicable | G17: À formaliser | I17: À calibrer | J17: Critique | K17: À calibrer | L17: V1.0
A18: D4.2.1 | B18: D4 | C18: Documentation des relations | D18: Contrats; commandes | E18: Mixte | F18: Applicable | G18: À formaliser | I18: À calibrer | J18: Importante | K18: À calibrer | L18: V1.0
A19: D4.3.1 | B19: D4 | C19: Gestion des incidents | D19: Litiges résolus ou non | E19: Mixte | F19: Applicable | G19: À formaliser | I19: À calibrer | J19: Importante | K19: À calibrer | L19: V1.0
A20: D4.4.1 | B20: D4 | C20: Réputation commerciale documentée | D20: Retours de tiers autorisés | E20: Qualitatif | F20: Applicable | G20: À formaliser | I20: À calibrer | J20: Secondaire | K20: À calibrer | L20: V1.0
A21: D5.1.1 | B21: D5 | C21: Niveau d’activité observé | D21: CA ou volume d’activité | E21: Quantitatif | F21: Applicable avec adaptation | G21: À formaliser | I21: À calibrer | J21: Importante | K21: À calibrer | L21: V1.0 | M21: Règles proportionnées au segment.
A22: D5.2.1 | B22: D5 | C22: Évolution de l’activité | D22: Variation dans le temps | E22: Quantitatif | F22: Applicable avec adaptation | G22: À formaliser | I22: À calibrer | J22: Importante | K22: À calibrer | L22: V1.0
A23: D5.3.1 | B23: D5 | C23: Concentration des revenus | D23: Part des principaux clients | E23: Quantitatif | F23: Applicable avec adaptation | G23: À formaliser | I23: À calibrer | J23: Importante | K23: À calibrer | L23: V1.0
A24: D5.4.1 | B24: D5 | C24: Fragilités observables | D24: Interruptions; dépendances | E24: Mixte | F24: Applicable | G24: À formaliser | I24: À calibrer | J24: Importante | K24: À calibrer | L24: V1.0
A25: D6.1.1 | B25: D6 | C25: Organisation adaptée | D25: Organisation observée | E25: Qualitatif | F25: Applicable avec adaptation | G25: À formaliser | I25: À calibrer | J25: Secondaire | K25: À calibrer | L25: V1.0 | M25: Ne pas confondre formalisation et crédibilité.
A26: D6.2.1 | B26: D6 | C26: Gestion administrative | D26: Documents et suivi | E26: Mixte | F26: Applicable avec adaptation | G26: À formaliser | I26: À calibrer | J26: Secondaire | K26: À calibrer | L26: V1.0
A27: D6.3.1 | B27: D6 | C27: Séparation des responsabilités | D27: Répartition des rôles | E27: Qualitatif | F27: Applicable avec adaptation | G27: À formaliser | I27: À calibrer | J27: Secondaire | K27: À calibrer | L27: V1.0
A28: D6.4.1 | B28: D6 | C28: Outils de suivi | D28: Tableaux; registres; logiciels | E28: Mixte | F28: Applicable avec adaptation | G28: À formaliser | I28: À calibrer | J28: Secondaire | K28: À calibrer | L28: V1.0

Sheet 03_Variables
A1: 03 — Pré-dictionnaire des variables
A2: Première structuration technique issue des variables principales du Manuel. Les identifiants et définitions détaillées doivent être consolidés avant production.
A4: Variable_ID | B4: Dimension | C4: Indicateur | D4: Nom variable | E4: Type technique | F4: Format | G4: Unité | H4: Source privilégiée | I4: Sources alternatives | J4: Preuve min. | K4: Criticité | L4: Applicabilité | M4: Fraîcheur | N4: Statut
A5: VAR-D1-01-01 | B5: D1 | C5: D1.1.1 | D5: Dénomination ou nom commercial | E5: Scoring | F5: Texte | H5: Déclaration + pièces | I5: Registres officiels | J5: À calibrer | K5: Critique | L5: Applicable | M5: À calibrer | N5: À formaliser
A6: VAR-D1-01-02 | B6: D1 | C6: D1.1.1 | D6: Forme juridique | E6: Scoring | F6: Catégorie | H6: Pièces administratives | I6: Déclaration corroborée | J6: À calibrer | K6: Importante | L6: Applicable | M6: À calibrer | N6: À formaliser
A7: VAR-D1-01-03 | B7: D1 | C7: D1.1.1 | D7: Numéro(s) officiel(s) d’identification | E7: Scoring | F7: Texte | H7: Registre/document officiel | I7: Autres pièces fiables | J7: À calibrer | K7: Critique | L7: Applicable avec adaptation | M7: À calibrer | N7: À formaliser
A8: VAR-D1-01-04 | B8: D1 | C8: D1.1.1 | D8: Statut d’enregistrement | E8: Scoring | F8: Catégorie | H8: Registre/document officiel | I8: Pièces administratives | J8: À calibrer | K8: Critique | L8: Applicable avec adaptation | M8: À calibrer | N8: À formaliser
A9: VAR-D1-02-01 | B9: D1 | C9: D1.2.1 | D9: Dirigeants | E9: Scoring | F9: Texte | H9: Déclaration + pièce | I9: Tiers autorisé | J9: À calibrer | K9: Importante | L9: Applicable | M9: À calibrer | N9: À formaliser
A10: VAR-D1-02-02 | B10: D1 | C10: D1.2.1 | D10: Représentants | E10: Descriptive | F10: Texte | H10: Déclaration + mandat | I10: Tiers autorisé | J10: À calibrer | K10: Secondaire | L10: Applicable avec adaptation | M10: À calibrer | N10: À formaliser
A11: VAR-D1-03-01 | B11: D1 | C11: D1.3.1 | D11: Adresse | E11: Scoring | F11: Texte | H11: Pièce/constat | I11: Déclaration corroborée | J11: À calibrer | K11: Importante | L11: Applicable | M11: À calibrer | N11: À formaliser
A12: VAR-D1-03-02 | B12: D1 | C12: D1.3.1 | D12: Lieu d’activité | E12: Scoring | F12: Texte | H12: Constat/visite | I12: Tiers/document | J12: À calibrer | K12: Importante | L12: Applicable | M12: À calibrer | N12: À formaliser
A13: VAR-D1-04-01 | B13: D1 | C13: D1.4.1 | D13: Date de début effectif de l’activité | E13: Scoring | F13: Date | H13: Historique de transactions | I13: Documents administratifs; contrats; factures | J13: À calibrer | K13: Importante | L13: Applicable | M13: À calibrer | N13: À formaliser
A14: VAR-D1-04-02 | B14: D1 | C14: D1.4.1 | D14: Durée d’activité | E14: Calculée | F14: Nombre | G14: Mois | H14: Calcul | I14: Date de début | J14: À calibrer | K14: Secondaire | L14: Applicable | M14: Dynamique | N14: À formaliser
A15: VAR-D2-01-01 | B15: D2 | C15: D2.1.1 | D15: Variables essentielles disponibles | E15: Calculée | F15: Nombre/Ratio | G15: % | H15: Dossier | I15: N/A | J15: À calibrer | K15: Importante | L15: Applicable | M15: Dynamique | N15: À formaliser
A16: VAR-D2-02-01 | B16: D2 | C16: D2.2.1 | D16: Écarts entre informations | E16: Contrôle | F16: Nombre | H16: Contrôles croisés | I16: N/A | J16: À calibrer | K16: Importante | L16: Applicable | M16: Dynamique | N16: À formaliser
A17: VAR-D2-02-02 | B17: D2 | C17: D2.2.1 | D17: Contradictions non résolues | E17: Contrôle | F17: Nombre | H17: Contrôles croisés | I17: N/A | J17: À calibrer | K17: Critique | L17: Applicable | M17: Dynamique | N17: À formaliser
A18: VAR-D2-03-01 | B18: D2 | C18: D2.3.1 | D18: Sources associées | E18: Traçabilité | F18: Nombre/Ratio | G18: % | H18: Métadonnées dossier | I18: N/A | J18: À calibrer | K18: Importante | L18: Applicable | M18: Dynamique | N18: À formaliser
A19: VAR-D2-03-02 | B19: D2 | C19: D2.3.1 | D19: Pièces associées | E19: Traçabilité | F19: Nombre/Ratio | G19: % | H19: Dossier preuves | I19: N/A | J19: À calibrer | K19: Importante | L19: Applicable | M19: Dynamique | N19: À formaliser
A20: VAR-D2-04-01 | B20: D2 | C20: D2.4.1 | D20: Date des données | E20: Traçabilité | F20: Date | H20: Métadonnées | I20: N/A | J20: À calibrer | K20: Secondaire | L20: Applicable | M20: Selon type de donnée | N20: À formaliser
A21: VAR-D3-01-01 | B21: D3 | C21: D3.1.1 | D21: Périodes d’activité observées | E21: Scoring | F21: Nombre | G21: Périodes | H21: Transactions/documents | I21: Déclaration corroborée | J21: À calibrer | K21: Importante | L21: Applicable | M21: Périodique | N21: À formaliser
A22: VAR-D3-02-01 | B22: D3 | C22: D3.2.1 | D22: Mois actifs | E22: Scoring | F22: Nombre | G22: Mois | H22: Transactions/documents | I22: Déclaration corroborée | J22: À calibrer | K22: Importante | L22: Applicable | M22: Périodique | N22: À formaliser
A23: VAR-D3-02-02 | B23: D3 | C23: D3.2.1 | D23: Interruptions | E23: Scoring | F23: Nombre | G23: Périodes | H23: Historique activité | I23: Déclaration corroborée | J23: À calibrer | K23: Importante | L23: Applicable | M23: Périodique | N23: À formaliser
A24: VAR-D3-03-01 | B24: D3 | C24: D3.3.1 | D24: Principaux clients ou sources d’activité | E24: Scoring | F24: Liste/Ratio | G24: % | H24: Ventes/contrats | I24: Déclaration corroborée | J24: À calibrer | K24: Importante | L24: Applicable avec adaptation | M24: Périodique | N24: À formaliser
A25: VAR-D3-04-01 | B25: D3 | C25: D3.4.1 | D25: Variations importantes d’activité | E25: Calculée | F25: Nombre/Ratio | G25: % | H25: Historique activité | I25: N/A | J25: À calibrer | K25: Importante | L25: Applicable | M25: Périodique | N25: À formaliser
A26: VAR-D4-01-01 | B26: D4 | C26: D4.1.1 | D26: Incidents documentés liés aux engagements | E26: Scoring | F26: Nombre | H26: Documents/tiers | I26: Déclaration corroborée | J26: À calibrer | K26: Critique | L26: Applicable | M26: Périodique | N26: À formaliser
A27: VAR-D4-02-01 | B27: D4 | C27: D4.2.1 | D27: Contrats disponibles | E27: Scoring | F27: Nombre/Ratio | G27: % | H27: Contrats | I27: Commandes | J27: À calibrer | K27: Importante | L27: Applicable avec adaptation | M27: Périodique | N27: À formaliser
A28: VAR-D4-02-02 | B28: D4 | C28: D4.2.1 | D28: Commandes disponibles | E28: Scoring | F28: Nombre/Ratio | G28: % | H28: Commandes | I28: Factures/contrats | J28: À calibrer | K28: Importante | L28: Applicable avec adaptation | M28: Périodique | N28: À formaliser
A29: VAR-D4-03-01 | B29: D4 | C29: D4.3.1 | D29: Litiges | E29: Scoring | F29: Nombre | H29: Documents/tiers | I29: Déclaration corroborée | J29: À calibrer | K29: Importante | L29: Applicable | M29: Périodique | N29: À formaliser
A30: VAR-D4-03-02 | B30: D4 | C30: D4.3.1 | D30: Statut de résolution des litiges | E30: Scoring | F30: Catégorie | H30: Dossier incident | I30: Tiers autorisé | J30: À calibrer | K30: Importante | L30: Applicable si litige | M30: Périodique | N30: À formaliser
A31: VAR-D4-04-01 | B31: D4 | C31: D4.4.1 | D31: Retours de tiers autorisés | E31: Scoring | F31: Catégorie/Texte | H31: Tiers autorisés | I31: Références documentées | J31: À calibrer | K31: Secondaire | L31: Applicable avec adaptation | M31: À calibrer | N31: À formaliser
A32: VAR-D5-01-01 | B32: D5 | C32: D5.1.1 | D32: Chiffre d’affaires ou volume d’activité | E32: Scoring | F32: Nombre | G32: FCFA / unité | H32: Documents comptables/ventes | I32: Transactions corroborées | J32: À calibrer | K32: Importante | L32: Applicable avec adaptation | M32: Périodique | N32: À formaliser
A33: VAR-D5-02-01 | B33: D5 | C33: D5.2.1 | D33: Variation de l’activité dans le temps | E33: Calculée | F33: Nombre/Ratio | G33: % | H33: Historique activité | I33: N/A | J33: À calibrer | K33: Importante | L33: Applicable avec adaptation | M33: Périodique | N33: À formaliser
A34: VAR-D5-03-01 | B34: D5 | C34: D5.3.1 | D34: Part du chiffre d’affaires des principaux clients | E34: Calculée | F34: Nombre/Ratio | G34: % | H34: Ventes par client | I34: Déclaration corroborée | J34: À calibrer | K34: Importante | L34: Applicable avec adaptation | M34: Périodique | N34: À formaliser
A35: VAR-D5-04-01 | B35: D5 | C35: D5.4.1 | D35: Interruptions significatives | E35: Scoring | F35: Nombre | H35: Historique activité | I35: Déclaration corroborée | J35: À calibrer | K35: Importante | L35: Applicable | M35: Périodique | N35: À formaliser
A36: VAR-D5-04-02 | B36: D5 | C36: D5.4.1 | D36: Dépendances critiques observables | E36: Scoring | F36: Liste/Catégorie | H36: Analyse activité | I36: Tiers/documents | J36: À calibrer | K36: Importante | L36: Applicable | M36: Périodique | N36: À formaliser
A37: VAR-D6-01-01 | B37: D6 | C37: D6.1.1 | D37: Organisation observée | E37: Scoring | F37: Catégorie | H37: Entretien/observation | I37: Documents internes | J37: À calibrer | K37: Secondaire | L37: Applicable avec adaptation | M37: À calibrer | N37: À formaliser
A38: VAR-D6-02-01 | B38: D6 | C38: D6.2.1 | D38: Documents de gestion administrative | E38: Scoring | F38: Liste/Ratio | G38: % | H38: Documents internes | I38: Observation | J38: À calibrer | K38: Secondaire | L38: Applicable avec adaptation | M38: À calibrer | N38: À formaliser
A39: VAR-D6-02-02 | B39: D6 | C39: D6.2.1 | D39: Suivi administratif | E39: Scoring | F39: Catégorie | H39: Documents/observation | I39: Entretien | J39: À calibrer | K39: Secondaire | L39: Applicable avec adaptation | M39: À calibrer | N39: À formaliser
A40: VAR-D6-03-01 | B40: D6 | C40: D6.3.1 | D40: Répartition des rôles | E40: Scoring | F40: Catégorie | H40: Organisation/entretien | I40: Documents internes | J40: À calibrer | K40: Secondaire | L40: Applicable avec adaptation | M40: À calibrer | N40: À formaliser
A41: VAR-D6-04-01 | B41: D6 | C41: D6.4.1 | D41: Outils de suivi utilisés | E41: Scoring | F41: Liste/Catégorie | H41: Observation | I41: Documents internes | J41: À calibrer | K41: Secondaire | L41: Applicable avec adaptation | M41: À calibrer | N41: À formaliser

Sheet 04_Preuves
A1: 04 — Paramètres de qualification des preuves
A2: Le niveau de preuve mesure la force du soutien de l’information, pas la qualité économique de l’entreprise.
A4: Niveau | B4: Libellé | C4: Définition opérationnelle | D4: Valeur IQP V1 | E4: Statut | F4: Règle clé | G4: Version | H4: Commentaire
A5: N1 | B5: Déclarée | C5: Information déclarée sans corroboration externe suffisante | D5: 25 | E5: À calibrer | F5: Ne constitue pas automatiquement une preuve faible au sens économique | G5: V1.0 | H5: Valeur utilisée pour l’IQP uniquement
A6: N2 | B6: Corroborée | C6: Information soutenue par des éléments secondaires cohérents | D6: 50 | E6: À calibrer | F6: La corroboration doit être traçable | G6: V1.0 | H6: Valeur utilisée pour l’IQP uniquement
A7: N3 | B7: Documentée | C7: Information soutenue par un document daté et exploitable | D7: 75 | E7: À calibrer | F7: Le document doit être relié à la variable | G7: V1.0 | H7: Valeur utilisée pour l’IQP uniquement
A8: N4 | B8: Vérifiée | C8: Information confirmée selon une procédure TOLBO ou par un tiers indépendant | D8: 100 | E8: À calibrer | F8: N4 ne signifie pas garantie absolument exacte | G8: V1.0 | H8: Valeur utilisée pour l’IQP uniquement

Sheet 05_IQP
A1: 05 — Paramètres IQP
A2: L’IQP est un indice distinct du Score Pass. Pondérations V1 à tester pendant le pilote.
A4: Code | B4: Composante | C4: Poids V1 | D4: Entrée attendue | E4: Échelle | F4: Statut | G4: Version
A5: E | B5: Étayage | C5: 0.4 | D5: Agrégation des niveaux de preuve | E5: 0–100 | F5: À calibrer | G5: V1.0
A6: C | B6: Couverture probatoire | C6: 0.2 | D6: Part des informations applicables suffisamment étayées | E6: 0–100 | F6: À calibrer | G6: V1.0
A7: F | B7: Fraîcheur | C7: 0.15 | D7: Actualité des preuves/données | E7: 0–100 | F7: À calibrer | G7: V1.0
A8: Co | B8: Cohérence | C8: 0.15 | D8: Cohérence interne et externe des informations | E8: 0–100 | F8: À calibrer | G8: V1.0
A9: T | B9: Traçabilité | C9: 0.1 | D9: Provenance et historique des informations | E9: 0–100 | F9: À calibrer | G9: V1.0
A10: TOTAL | C10: =SUM(C5:C9) -> 1
A12: Calculateur IQP (exemple technique)
A13: Composante | B13: Valeur /100 | C13: Poids | D13: Contribution
A14: Étayage | B14: 80 | C14: =C5 -> 0.4 | D14: =B14*C14 -> 32
A15: Couverture | B15: 70 | C15: =C6 -> 0.2 | D15: =B15*C15 -> 14
A16: Fraîcheur | B16: 90 | C16: =C7 -> 0.15 | D16: =B16*C16 -> 13.5
A17: Cohérence | B17: 75 | C17: =C8 -> 0.15 | D17: =B17*C17 -> 11.25
A18: Traçabilité | B18: 85 | C18: =C9 -> 0.1 | D18: =B18*C18 -> 8.5
A19: IQP calculé | B19: =SUM(D14:D18) -> 79.25

Sheet 06_Normalisation
A1: 06 — Bibliothèque des règles de normalisation
A2: Chaque indicateur doit être rattaché à une règle versionnée. Les paramètres numériques restent à calibrer.
A4: Rule_ID | B4: Famille | C4: Sens | D4: Paramètre 1 | E4: Paramètre 2 | F4: Paramètre 3 | G4: Formule/description | H4: Statut | I4: Version | J4: Applicable aux indicateurs | K4: Commentaire
A5: NORM-BIN-01 | B5: Binaire | C5: Croissant | D5: Valeur défavorable | E5: Valeur favorable | G5: Association directe à des notes | H5: À calibrer | I5: V1.0
A6: NORM-CAT-01 | B6: Catégories ordonnées | C6: Croissant | D6: Liste catégories | E6: Notes associées | G6: Table de correspondance | H6: À calibrer | I6: V1.0
A7: NORM-THR-01 | B7: Seuils | C7: Selon indicateur | D7: Borne 1 | E7: Borne 2 | F7: Autres bornes | G7: Notes par zone | H7: À calibrer | I7: V1.0
A8: NORM-LIN-UP | B8: Linéaire | C8: Croissant | D8: Minimum | E8: Maximum | G8: Interpolation 0–100 | H8: À calibrer | I8: V1.0
A9: NORM-LIN-DN | B9: Linéaire | C9: Décroissant | D9: Minimum | E9: Maximum | G9: Interpolation 100–0 | H9: À calibrer | I9: V1.0
A10: NORM-OPT-01 | B10: Zone optimale | C10: Zone optimale | D10: Borne basse | E10: Borne haute | F10: Pente hors zone | G10: 100 dans la zone, décroissance hors zone | H10: À calibrer | I10: V1.0
A11: NORM-CTX-01 | B11: Contextuelle | C11: Selon segment | D11: Segment | E11: Paramètres segment | G11: Règle spécifique versionnée | H11: À calibrer | I11: V1.0

Sheet 07_Agregation
A1: 07 — Agrégation, pondération et couverture
A2: Feuille de référence technique avec démonstrateur. L’arrondi externe intervient uniquement en fin de calcul.
A4: Code | B4: Dimension | C4: Score /100 | D4: Poids | E4: Contribution | F4: Applicable ? | G4: Statut | H4: Commentaire
A5: D1 | B5: Identité & existence | C5: 90 | D5: ='01_Dimensions'!D5 -> 0.15 | E5: =C5*D5 -> 13.5 | F5: Oui | G5: Évaluable
A6: D2 | B6: Traçabilité & qualité des données | C6: 70 | D6: ='01_Dimensions'!D6 -> 0.2 | E6: =C6*D6 -> 14 | F6: Oui | G6: Évaluable
A7: D3 | B7: Activité & régularité économique | C7: 80 | D7: ='01_Dimensions'!D7 -> 0.2 | E7: =C7*D7 -> 16 | F7: Oui | G7: Évaluable
A8: D4 | B8: Discipline & engagements | C8: 75 | D8: ='01_Dimensions'!D8 -> 0.2 | E8: =C8*D8 -> 15 | F8: Oui | G8: Évaluable
A9: D5 | B9: Performance & résilience | C9: 65 | D9: ='01_Dimensions'!D9 -> 0.15 | E9: =C9*D9 -> 9.75 | F9: Oui | G9: Évaluable
A10: D6 | B10: Formalisation & gouvernance | C10: 60 | D10: ='01_Dimensions'!D10 -> 0.1 | E10: =C10*D10 -> 6 | F10: Oui | G10: Évaluable
A11: TOTAL | D11: =SUM(D5:D10) -> 1 | E11: =SUM(E5:E10) -> 74.25
A12: Score Pass externe | C12: =ROUND(E11,0) -> 74
A15: Règle | B15: Définition | C15: Traitement moteur | D15: Statut
A16: Score agrégé | B16: Σ(wᵢ × Sᵢ), Σwᵢ=1 | C16: Calcul décimal interne; arrondi final seulement | D16: Établie
A17: Non applicable | B17: Élément hors périmètre pertinent | C17: Exclure numérateur et dénominateur; renormaliser si autorisé | D17: Établie
A18: Non évaluable | B18: Applicable mais information/preuve insuffisante | C18: Vérifier couverture et criticité avant agrégation | D18: Établie
A19: Donnée manquante | B19: Information pertinente absente | C19: Ne jamais convertir automatiquement en 0 | D19: Établie
A20: Couverture | B20: Poids évalué / poids applicable | C20: Calcul global et par dimension | D20: Établie
A21: Seuil de couverture | B21: Minimum requis pour score global | C21: À calibrer | D21: À calibrer

Sheet 08_Statuts
A1: 08 — Statuts fonctionnels
A2: Nomenclature à utiliser dans la base, les règles métier et les interfaces.
A4: Catégorie | B4: Code technique | C4: Libellé affiché | D4: Définition / effet | E4: Valeur automatique ? | F4: Version | G4: Statut | H4: Commentaire
A5: Disponibilité | B5: EVALUABLE | C5: Évaluable | D5: Information suffisante pour appliquer la règle | E5: Non | F5: V1.0 | G5: Actif
A6: Disponibilité | B6: NOT_APPLICABLE | C6: Non applicable | D6: Élément non pertinent selon l’applicabilité | E6: Non | F6: V1.0 | G6: Actif
A7: Disponibilité | B7: NOT_EVALUABLE_MISSING | C7: Non évaluable — information manquante | D7: Applicable mais donnée absente | E7: Non | F7: V1.0 | G7: Actif
A8: Disponibilité | B8: NOT_EVALUABLE_EVIDENCE | C8: Non évaluable — preuve insuffisante | D8: Applicable mais niveau de preuve insuffisant | E8: Non | F8: V1.0 | G8: Actif
A9: Disponibilité | B9: COLD_START | C9: Historique insuffisant / cold start | D9: Historique insuffisant pour certaines mesures | E9: Non | F9: V1.0 | G9: Actif
A10: Disponibilité | B10: TEMP_UNAVAILABLE | C10: Temporairement indisponible | D10: Information indisponible temporairement | E10: Non | F10: V1.0 | G10: Actif
A11: Disponibilité | B11: REFUSED | C11: Refus de transmission | D11: Entreprise refuse une information | E11: Non | F11: V1.0 | G11: Actif
A12: Disponibilité | B12: UNDER_VERIFICATION | C12: Sous vérification | D12: Contrôle complémentaire en cours | E12: Non | F12: V1.0 | G12: Actif
A13: Dossier | B13: IN_PROGRESS | C13: Évaluation en cours | D13: Collecte/analyse non terminée | E13: Oui | F13: V1.0 | G13: Actif
A14: Dossier | B14: VERIFICATION | C14: Sous vérification | D14: Contrôles complémentaires en cours | E14: Oui | F14: V1.0 | G14: Actif
A15: Dossier | B15: SUSPENDED | C15: Évaluation suspendue | D15: Traitement interrompu temporairement | E15: Oui | F15: V1.0 | G15: Actif
A16: Dossier | B16: PROFILE_BUILDING | C16: Profil en constitution | D16: Historique insuffisant pour certaines dimensions | E16: Oui | F16: V1.0 | G16: Actif
... A20: Dossier | B20: INTERRUPTED | C20: Évaluation interrompue | D20: Dossier clôturé sans finalisation | E20: Oui | F20: V1.0 | G20: Actif

Sheet 09_Hard_Gates
A1: 09 — Matrice des conditions obligatoires de passage (hard gates)
A2: Les hard gates opèrent hors du mécanisme de compensation numérique.
A4: Code | B4: Condition V1 | C4: Nature par défaut | D4: Remédiable ? | E4: Effet moteur | F4: Autorité minimale | G4: Preuves requises | H4: Statut V1 | I4: Version | J4: Commentaire
A5: HG1 | B5: Identité ou existence impossible à établir | C5: Suspensive / bloquante | D5: Oui selon cause | E5: Suspendre ou empêcher le Score Pass global | F5: Responsable Méthode | G5: Éléments du dossier + contrôles | H5: À calibrer | I5: V1.0 | J5: Faible formalisation ≠ identité impossible
A6: HG2 | B6: Activité manifestement incompatible avec le périmètre légal ou méthodologique | C6: Bloquante | D6: Selon cause | E6: Interrompre l’évaluation normale | F6: Responsable Méthode / Comité si sensible | G6: Éléments établissant l’incompatibilité | H6: Actif | I6: V1.0
A7: HG3 | B7: Falsification ou manipulation substantielle établie | C7: Bloquante | D7: Selon décision | E7: Bloquer / escalader | F7: Responsable Méthode + Comité si sensible | G7: Vérifications documentées | H7: Actif | I7: V1.0 | J7: Incohérence ≠ falsification
A8: HG4 | B8: Refus d’une information critique indispensable | C8: Suspensive / bloquante | D8: Oui | E8: Suspendre ou bloquer selon criticité | F8: Responsable Méthode | G8: Trace du refus + criticité de la variable | H8: À calibrer | I8: V1.0

Sheet 10_Anomalies_Exceptions
A1: 10 — Anomalies, escalades et exceptions
A2: Référentiel minimal pour les workflows de contrôle et de gouvernance.
A4: Code | B4: Niveau | C4: Définition | D4: Effet par défaut | E4: Escalade | F4: Version
A5: A1 | B5: Mineure | C5: Écart de faible criticité | D5: Documenter et traiter dans le flux normal | E5: Non, sauf récurrence | F5: V1.0
A6: A2 | B6: Significative | C6: Écart pouvant affecter l’évaluation | D6: Vérification complémentaire | E6: Selon impact | F6: V1.0
A7: A3 | B7: Critique | C7: Écart susceptible d’invalider ou suspendre l’évaluation | D7: Escalade et décision formelle | E7: Oui | F7: V1.0
A8: FLOW | B8: Workflow | C8: Détection → Enregistrement → Qualification → Analyse d’impact → Vérification → Décision → Clôture / réserve / escalade | F8: V1.0
A11: Objet | B11: Règle standard | C11: Autorisation | D11: Traçabilité | E11: Peut modifier un score ? | F11: Peut modifier un paramètre global ? | G11: Historique | H11: Statut | I11: Version
A12: Escalade | B12: Renforcement du niveau de contrôle | C12: Selon RACI | D12: Obligatoire | E12: Indirectement après vérification | F12: Non | G12: Oui | H12: Actif | I12: V1.0
A13: Exception méthodologique | B13: Traitement atypique documenté | C13: Responsable Méthode / Comité selon criticité | D13: Obligatoire | E13: Oui si règle approuvée | F13: Non | G13: Oui | H13: Actif | I13: V1.0
A14: Correction | B14: Réparation d’une erreur sur une évaluation | C14: Selon workflow | D14: Obligatoire | E14: Oui avec recalcul | F14: Non | G14: Score initial conservé | H14: Actif | I14: V1.0
A15: Modification du modèle | B15: Évolution générale des règles | C15: Comité compétent | D15: Obligatoire + versionnage | E15: Sur les nouvelles évaluations | F15: Oui | G15: Anciennes versions conservées | H15: Actif | I15: V1.0

Sheet 11_Fraicheur
A1: 11 — Fraîcheur des données et évaluations
A2: Les durées définitives doivent être calibrées par type de donnée et usage.
A4: Code | B4: Libellé | C4: Définition | D4: Durée par défaut | E4: Unité | F4: Déclencheur événementiel | G4: Statut | H4: Version
A5: CURRENT | B5: À jour | C5: Informations suffisamment récentes selon la règle active | E5: Jours/Mois | F5: Oui | G5: À calibrer | H5: V1.0
A6: REFRESH | B6: À actualiser | C6: Certaines informations doivent être mises à jour | E6: Jours/Mois | F6: Oui | G6: À calibrer | H6: V1.0
A7: EXPIRED | B7: Expiré | C7: Évaluation ne devant plus être présentée comme actuelle | E7: Jours/Mois | F7: Oui | G7: À calibrer | H7: V1.0
A10: Événement déclencheur | B10: Action minimale | C10: Automatisable ? | D10: Statut
A11: Changement de dirigeant ou contrôle | B11: Marquer à réexaminer | C11: Oui si événement connu | D11: À formaliser
A12: Changement significatif d’activité | B12: Marquer à réexaminer | C12: Partiel | D12: À formaliser
A13: Changement de localisation | B13: Actualiser identité/localisation | C13: Oui si donnée structurée | D13: À formaliser
A14: Interruption significative | B14: Réévaluer D3/D5 | C14: Partiel | D14: À formaliser
A15: Variation majeure d’activité | B15: Réévaluer indicateurs concernés | C15: Partiel | D15: À formaliser
A16: Perte d’un client majeur | B16: Réévaluer concentration/résilience | C16: Partiel | D16: À formaliser
A17: Incident majeur d’exécution | B17: Réévaluer D4/D5 | C17: Partiel | D17: À formaliser
A18: Nouvelle anomalie critique | B18: Passer sous vérification | C18: Oui | D18: À formaliser

Sheet 12_Versionnage
A1: 12 — Versionnage des paramètres méthodologiques
A2: Toute évaluation officielle doit être reproductible avec la version qui l’a produite.
A4: Version | B4: Date approbation | C4: Date effet | D4: Niveau | E4: État | F4: Description | G4: Rétroactivité | H4: Autorité
A5: V1.0 | D5: Baseline | E5: Pré-pilote | F5: Première version opérationnelle du paramétrage | G5: Non | H5: À définir
A6: V1.1 | D6: Mineure | E6: Future | G6: Non | H6: À définir
A7: V2.0 | D7: Majeure | E7: Future | G7: Non | H7: À définir
A10: Classe modification | B10: Définition | C10: Exemple | D10: Version moteur requise ? | E10: Test impact | F10: Approbation
A11: M1 — Mineure | B11: Correction sans effet méthodologique sur le résultat | C11: Typographie / clarification | D11: Pas nécessairement | E11: Non ou limité | F11: Responsable Méthode
A12: M2 — Intermédiaire | B12: Effet limité/localisé | C12: Ajustement règle d’indicateur | D12: Oui | E12: Oui | F12: Responsable Méthode + validation prévue
A13: M3 — Majeure | B13: Effet significatif sur score/interprétation | C13: Poids, dimension, hard gate, architecture | D13: Oui, version majeure selon cas | E13: Oui | F13: Comité compétent
A14: Éditoriale | B14: Aucun effet sur règles/calcul | C14: Correction rédactionnelle | D14: Non | E14: Non | F14: Selon maîtrise documentaire

Sheet 13_A_Calibrer
A1: 13 — Registre des paramètres à calibrer / finaliser
A2: Liste de contrôle avant passage en production. L’ingénieur ne doit pas définir ces valeurs de sa propre initiative.
A4: ID | B4: Paramètre | C4: Niveau | D4: Décision attendue | E4: Source de calibration | F4: Blocage production ? | G4: Statut
A5: CAL-001 | B5: Liste exhaustive et codification définitive des variables | C5: Variable | D5: Valider dictionnaire complet | E5: Pilote + revue méthodologique | F5: Oui | G5: À finaliser
A6: CAL-002 | B6: Formules détaillées des 24 indicateurs | C6: Indicateur | D6: Formaliser chaque calcul | E6: Manuel + pilote | F6: Oui | G6: À finaliser
A7: CAL-003 | B7: Seuils de normalisation par indicateur | C7: Indicateur | D7: Fixer bornes/fonctions | E7: Distributions pilote | F7: Oui | G7: À calibrer
A8: CAL-004 | B8: Poids internes indicateurs / sous-dimensions | C8: Agrégation | D8: Fixer pondérations | E8: Sensibilité + pilote | F8: Oui | G8: À calibrer
A9: CAL-005 | B9: Seuil minimal de couverture | C9: Global / dimension | D9: Fixer seuil(s) | E9: Pilote | F9: Oui | G9: À calibrer
A10: CAL-006 | B10: Niveaux minimaux de preuve par variable critique | C10: Preuve | D10: Fixer exigences | E10: Pilote + usages partenaires | F10: Oui | G10: À calibrer
A11: CAL-007 | B11: Bornes des classes d’interprétation | C11: Restitution | D11: Fixer ou confirmer absence de classes | E11: Distribution + compréhension partenaire | F11: Non pour pilote | G11: À calibrer
A12: CAL-008 | B12: Durées de fraîcheur | C12: Donnée / évaluation | D12: Fixer règles temporelles | E12: Pilote + partenaires | F12: Oui | G12: À calibrer
A13: CAL-009 | B13: Règles sectorielles spécifiques | C13: Segmentation | D13: Définir si nécessaires | E13: Pilote multi-secteurs | F13: Selon usage | G13: À tester
A14: CAL-010 | B14: Délais de traitement contestation | C14: Gouvernance | D14: Fixer SLA opérationnel | E14: Organisation TOLBO | F14: Non moteur calcul | G14: À définir

Sheet 14_Config_Moteur
A1: 14 — Paramètres globaux du moteur
A2: Clés de configuration de haut niveau. Les valeurs marquées à calibrer doivent être externes au code.
A4: Param_Key | B4: Description | C4: Valeur V1 | D4: Type | E4: Version | F4: Statut
A5: score.scale.min | B5: Minimum Score Pass | C5: 0 | D5: Integer | E5: V1.0 | F5: Établi
A6: score.scale.max | B6: Maximum Score Pass | C6: 100 | D6: Integer | E6: V1.0 | F6: Établi
A7: score.output.format | B7: Format externe | C7: X/100 | D7: String | E7: V1.0 | F7: Établi
A8: score.rounding.stage | B8: Moment de l’arrondi | C8: Final uniquement | D8: Enum | E8: V1.0 | F8: Établi
A9: iqp.scale.min | B9: Minimum IQP | C9: 0 | D9: Integer | E9: V1.0 | F9: Établi
A10: iqp.scale.max | B10: Maximum IQP | C10: 100 | D10: Integer | E10: V1.0 | F10: Établi
A11: coverage.threshold.global | B11: Seuil couverture global minimum | D11: Decimal | E11: V1.0 | F11: À calibrer
A12: coverage.threshold.dimension | B12: Seuil couverture par dimension | D12: Decimal | E12: V1.0 | F12: À calibrer
A13: missing.as_zero | B13: Convertir donnée manquante en zéro | C13: FALSE | D13: Boolean | E13: V1.0 | F13: Établi
A14: na.renormalize | B14: Autoriser renormalisation des poids pour NA | C14: TRUE | D14: Boolean | E14: V1.0 | F14: Établi
A15: non_evaluable.renormalize | B15: Renormaliser automatiquement le non-évaluable | C15: FALSE | D15: Boolean | E15: V1.0 | F15: Établi
A16: hard_gate.blocks_compensation | B16: Hard gates hors compensation | C16: TRUE | D16: Boolean | E16: V1.0 | F16: Établi
A17: historical_scores.retroactive | B17: Modifier scores historiques avec nouvelle version | C17: FALSE | D17: Boolean | E17: V1.0 | F17: Établi
A18: test_rules.affect_production | B18: Règles expérimentales affectent scores officiels | C18: FALSE | D18: Boolean | E18: V1.0 | F18: Établi
A19: partner.auto_decision | B19: Produire décision automatique financement/investissement | C19: FALSE | D19: Boolean | E19: V1.0 | F19: Établi

Sheet 15_Sorties
A1: 15 — Schéma minimal des sorties Score Pass
A2: Champs obligatoires de la restitution et de l’échange technique.
A4: Field_Key | B4: Libellé | C4: Type | D4: Obligatoire | E4: Condition | F4: Exemple | G4: Version | H4: Commentaire
A5: enterprise_id | B5: Identifiant entreprise | C5: String | D5: Oui | E5: Toujours | F5: ENT-00001 | G5: V1.0
A6: evaluation_id | B6: Identifiant évaluation | C6: String | D6: Oui | E6: Toujours | F6: SP-2026-00001 | G6: V1.0 | H6: Unique par évaluation
A7: model_version | B7: Version méthodologique | C7: String | D7: Oui | E7: Toujours | F7: V1.0 | G7: V1.0
A8: evaluation_date | B8: Date d’évaluation | C8: Date | D8: Oui | E8: Toujours | F8: 2026-08-31 | G8: V1.0
A9: observation_period | B9: Période observée | C9: String/DateRange | D9: Oui | E9: Toujours | F9: 2026-01 à 2026-06 | G9: V1.0
A10: dossier_status | B10: Statut dossier | C10: Enum | D10: Oui | E10: Toujours | F10: SCORE_PRODUCED | G10: V1.0
A11: score_pass | B11: Score Pass | C11: Decimal/Integer | D11: Conditionnel | E11: Si score global produit | F11: 74 | G11: V1.0 | H11: Restitution : 74/100
A12: dimension_scores | B12: Scores D1–D6 | C12: Object/List | D12: Oui si évaluables | E12: Selon applicabilité | F12: D1=90… | G12: V1.0
A13: iqp | B13: Indice de Qualité des Preuves | C13: Decimal | D13: Oui | E13: Si évaluation | F13: 78 | G13: V1.0 | H13: Distinct du Score Pass
A14: coverage | B14: Couverture méthodologique | C14: Decimal | D14: Oui | E14: Si évaluation | F14: 0.92 | G14: V1.0
A15: freshness_status | B15: Statut fraîcheur | C15: Enum | D15: Oui | E15: Toujours | F15: CURRENT | G15: V1.0
A16: limitations | B16: Réserves / limites | C16: Text/List | D16: Oui | E16: Peut être vide si aucune | F16: — | G16: V1.0
A17: mandatory_notice | B17: Mention méthodologique | C17: String | D17: Oui | E17: Restitution externe | F17: Texte standard | G17: V1.0 | H17: Ne pas supprimer
